nasbio/__init__.py
nasbio/app/__init__.py
nasbio/celery.py
nasbio/config.py
nasbio/db/__init__.py
nasbio/db/async_session.py
nasbio/db/base_class.py
nasbio/db/session.py
nasbio/events/__init__.py
nasbio/events/base_consumer.py
nasbio/events/base_publisher.py
nasbio/events/types.py
nasbio/sqlalchemy.py
nasbio/strawberry.py
nasbio/utils.py
nasbio-0.1.29.dist-info/WHEEL
nasbio-0.1.29.dist-info/METADATA
nasbio-0.1.29.dist-info/RECORD
